<?xml version="1.0" encoding="UTF-8" ?>
<paths xmlns:android="http://schemas.android.com/apk/res/android">
	<!-- External paths for images and movies -->
	<external-path name="my_images" path="Android/data/com.ezfactory.ezgo/files/Pictures/" />
	<external-path name="my_movies" path="Movies/" />
	<external-path name="external_files" path="." />

	<!-- Internal files directory -->
	<files-path name="languages" path="languages/" />
	<files-path name="images" path="images/" />
	<files-path name="audits" path="audits/" />
	<files-path name="checklists" path="checklists/" />
	<files-path name="cache" path="cache/" />
	<files-path name="pdf" path="pdf/" />
	<files-path name="media" path="media/" />
</paths>
